Workbook

Sheet README
A1: SOA 2021 Case Study - Cleaned Data Pack
A3: Purpose
A4: This workbook reorganizes the SOA 2021 Student Research Case Study data for the parametric health insurance project. It keeps the variables aligned with the intended methodology: background analysis, product market, assumptions, correlation matrix, PCA, Monte Carlo simulation, and premium/revenue analysis.
A8: Research workflow used in project
A9: 1.1 Background analysis | B9: Use macroeconomic, population, education, healthcare spending, and company financial data.
A10: 1.2 Product market | B10: Use population, healthcare spending per person, savings rate, and market-size assumptions.
A11: 1.3 Assumptions | B11: Use Blood Pressure, Diabetes, and Cholesterol as trigger-related health indicators.
A12: 1.4 Methodology | B12: Build correlation matrix, PCA input, and Monte Carlo-ready variables.
A13: 2. Product design | B13: Parametric health insurance for governments/healthcare organizations.
A14: 2.2 Design elements | B14: Triggers: Blood Pressure, Diabetes Prevalence, Cholesterol. Index: discrete health index. Payout: 1120 × excess over estimated trigger level.
A15: 3.1 Premium and revenue analysis | B15: Premium based on equivalence principle: expected payout plus loading.
A16: 3.2 Potential market analysis | B16: Use population and revenue assumptions to assess future opportunity.
A18: Key source workbook sheets
A19: Raw health triggers | B19: Triggers!A52:Q94 | C19: Blood pressure, diabetes, cholesterol
A20: Market/economic data | B20: Economic and Population Data | C20: GDP, GNI, CPI, population, healthcare spending, savings rate, interest rates
A21: Company financials | B21: NEW.WORLD Income Statement / Balance Sheet | C21: Revenue, claims, expenses, reserves, equity

Sheet Raw_Triggers
A1: Year | B1: Country | C1: Male Systolic | D1: Male Diastolic | E1: Female Systolic | F1: Female Diastolic | G1: Diabetes Male | H1: Diabetes Female | I1: Male HDL | J1: Male Non-HDL | K1: Female HDL | L1: Female Non-HDL
A2: 2011 | B2: Ambernϊa | C2: 130.4 | D2: 78.7 | E2: 121.3 | F2: 74.6 | G2: 0.063 | H2: 0.0403 | I2: 1.2785929 | J2: 3.7332371 | K2: 1.5975788 | L2: 3.4696812
A3: 2011 | B3: Palȍmϊnϊa | C3: 132.2 | D3: 81.7 | E3: 126.5 | F3: 79.2 | G3: 0.0715 | H3: 0.07 | I3: 1.2685612 | J3: 3.833104 | K3: 1.4715248 | L3: 3.6361546
A4: 2012 | B4: Ambernϊa | C4: 130.2 | D4: 78.5 | E4: 121 | F4: 74.5 | G4: 0.0631 | H4: 0.0401 | I4: 1.2793259 | J4: 3.6964064 | K4: 1.6031297 | L4: 3.4401813
A5: 2012 | B5: Palȍmϊnϊa | C5: 132.3 | D5: 81.7 | E5: 126.3 | F5: 79.1 | G5: 0.073 | H5: 0.0709 | I5: 1.2677311 | J5: 3.819167 | K5: 1.474848 | L5: 3.6163203
A6: 2013 | B6: Ambernϊa | C6: 129.9 | D6: 78.4 | E6: 120.6 | F6: 74.3 | G6: 0.0632 | H6: 0.0398 | I6: 1.2805516 | J6: 3.6602844 | K6: 1.6091194 | L6: 3.4110621
A7: 2013 | B7: Palȍmϊnϊa | C7: 132.4 | D7: 81.6 | E7: 126.2 | F7: 79 | G7: 0.0746 | H7: 0.0718 | I7: 1.2669251 | J7: 3.8047788 | K7: 1.4781146 | L7: 3.5959286
A8: 2014 | B8: Ambernϊa | C8: 129.6 | D8: 78.3 | E8: 120.3 | F8: 74.2 | G8: 0.0633 | H8: 0.0396 | I8: 1.2822021 | J8: 3.6239947 | K8: 1.615486 | L8: 3.3818798
A9: 2014 | B9: Palȍmϊnϊa | C9: 132.4 | D9: 81.6 | E9: 126 | F9: 79 | G9: 0.0761 | H9: 0.0727 | I9: 1.2661168 | J9: 3.7894993 | K9: 1.4813261 | L9: 3.574726
A10: 2015 | B10: Ambernϊa | C10: 129.3 | D10: 78.2 | E10: 120 | F10: 74.1 | G10: 0.0632 | H10: 0.0394 | I10: 1.2840503 | J10: 3.5870695 | K10: 1.6220312 | L10: 3.3523132
A11: 2015 | B11: Palȍmϊnϊa | C11: 132.5 | D11: 81.6 | E11: 125.8 | F11: 78.9 | G11: 0.0776 | H11: 0.0735 | I11: 1.2653253 | J11: 3.7731003 | K11: 1.4844522 | L11: 3.5526492
A12: 2016 | B12: Ambernϊa | C12: 129 | D12: 78 | E12: 119.6 | F12: 74 | G12: 0.0633 | H12: 0.0392 | I12: 1.2860153 | J12: 3.5495036 | K12: 1.6287047 | L12: 3.3224722
A13: 2016 | B13: Palȍmϊnϊa | C13: 132.6 | D13: 81.5 | E13: 125.6 | F13: 78.8 | G13: 0.0791 | H13: 0.0744 | I13: 1.264503 | J13: 3.7555895 | K13: 1.4875329 | L13: 3.5298034
... A21: 2020 | B21: Palȍmϊnϊa | C21: 132.9 | D21: 81.4 | E21: 124.7 | F21: 78.6 | G21: 0.0853 | H21: 0.078 | I21: 1.2615089 | J21: 3.6769312 | K21: 1.5000203 | L21: 3.4331173

Sheet Model_Input
A1: Year | B1: Country | C1: Avg Systolic | D1: Avg Diastolic | E1: Avg Diabetes | F1: Avg HDL | G1: Avg Non-HDL | H1: BP Component | I1: Cholesterol Ratio | J1: Health Index (0-100) | K1: Discrete Health Index | L1: Trigger Threshold | M1: Excess over Estimate | N1: Payout = 1120 × Excess
A2: 2011 | B2: Ambernϊa | C2: =AVERAGE(Raw_Triggers!C2,Raw_Triggers!E2) -> 125.85 | D2: =AVERAGE(Raw_Triggers!D2,Raw_Triggers!F2) -> 76.65 | E2: =AVERAGE(Raw_Triggers!G2,Raw_Triggers!H2) -> 0.05165 | F2: =AVERAGE(Raw_Triggers!I2,Raw_Triggers!K2) -> 1.4380859 | G2: =AVERAGE(Raw_Triggers!J2,Raw_Triggers!L2) -> 3.6014592 | H2: =C2+0.5*D2 -> 164.175 | I2: =G2/F2 -> 2.5043422 | J2: =40*(H2-MIN($H$2:$H$21))/(MAX($H$2:$H$21)-MIN($H$2:$H$21))+30*(E2-MIN($E$2:$E$21))/(MAX($E$2:$E$21)-MIN($E$2:$E$21))+30*(I2-MIN($I$2:$I$21))/(MAX($I$2:$I$21)-MIN($I$2:$I$21)) -> 32.404847 | K2: =IF(J2<33,"Low",IF(J2<66,"Medium","High")) -> Low | L2: =Assumptions!$B$9 -> 70 | M2: =MAX(0,J2-L2) -> 0 | N2: =1120*M2 -> 0
A3: 2011 | B3: Palȍmϊnϊa | C3: =AVERAGE(Raw_Triggers!C3,Raw_Triggers!E3) -> 129.35 | D3: =AVERAGE(Raw_Triggers!D3,Raw_Triggers!F3) -> 80.45 | E3: =AVERAGE(Raw_Triggers!G3,Raw_Triggers!H3) -> 0.07075 | F3: =AVERAGE(Raw_Triggers!I3,Raw_Triggers!K3) -> 1.370043 | G3: =AVERAGE(Raw_Triggers!J3,Raw_Triggers!L3) -> 3.7346293 | H3: =C3+0.5*D3 -> 169.575 | I3: =G3/F3 -> 2.7259212 | J3: =40*(H3-MIN($H$2:$H$21))/(MAX($H$2:$H$21)-MIN($H$2:$H$21))+30*(E3-MIN($E$2:$E$21))/(MAX($E$2:$E$21)-MIN($E$2:$E$21))+30*(I3-MIN($I$2:$I$21))/(MAX($I$2:$I$21)-MIN($I$2:$I$21)) -> 89.278689 | K3: =IF(J3<33,"Low",IF(J3<66,"Medium","High")) -> High | L3: =Assumptions!$B$9 -> 70 | M3: =MAX(0,J3-L3) -> 19.278689 | N3: =1120*M3 -> 21592.131
A4: 2012 | B4: Ambernϊa | C4: =AVERAGE(Raw_Triggers!C4,Raw_Triggers!E4) -> 125.6 | D4: =AVERAGE(Raw_Triggers!D4,Raw_Triggers!F4) -> 76.5 | E4: =AVERAGE(Raw_Triggers!G4,Raw_Triggers!H4) -> 0.0516 | F4: =AVERAGE(Raw_Triggers!I4,Raw_Triggers!K4) -> 1.4412278 | G4: =AVERAGE(Raw_Triggers!J4,Raw_Triggers!L4) -> 3.5682939 | H4: =C4+0.5*D4 -> 163.85 | I4: =G4/F4 -> 2.4758708 | J4: =40*(H4-MIN($H$2:$H$21))/(MAX($H$2:$H$21)-MIN($H$2:$H$21))+30*(E4-MIN($E$2:$E$21))/(MAX($E$2:$E$21)-MIN($E$2:$E$21))+30*(I4-MIN($I$2:$I$21))/(MAX($I$2:$I$21)-MIN($I$2:$I$21)) -> 29.138402 | K4: =IF(J4<33,"Low",IF(J4<66,"Medium","High")) -> Low | L4: =Assumptions!$B$9 -> 70 | M4: =MAX(0,J4-L4) -> 0 | N4: =1120*M4 -> 0
A5: 2012 | B5: Palȍmϊnϊa | C5: =AVERAGE(Raw_Triggers!C5,Raw_Triggers!E5) -> 129.3 | D5: =AVERAGE(Raw_Triggers!D5,Raw_Triggers!F5) -> 80.4 | E5: =AVERAGE(Raw_Triggers!G5,Raw_Triggers!H5) -> 0.07195 | F5: =AVERAGE(Raw_Triggers!I5,Raw_Triggers!K5) -> 1.3712895 | G5: =AVERAGE(Raw_Triggers!J5,Raw_Triggers!L5) -> 3.7177437 | H5: =C5+0.5*D5 -> 169.5 | I5: =G5/F5 -> 2.7111297 | J5: =40*(H5-MIN($H$2:$H$21))/(MAX($H$2:$H$21)-MIN($H$2:$H$21))+30*(E5-MIN($E$2:$E$21))/(MAX($E$2:$E$21)-MIN($E$2:$E$21))+30*(I5-MIN($I$2:$I$21))/(MAX($I$2:$I$21)-MIN($I$2:$I$21)) -> 89.214142 | K5: =IF(J5<33,"Low",IF(J5<66,"Medium","High")) -> High | L5: =Assumptions!$B$9 -> 70 | M5: =MAX(0,J5-L5) -> 19.214142 | N5: =1120*M5 -> 21519.839
A6: 2013 | B6: Ambernϊa | C6: =AVERAGE(Raw_Triggers!C6,Raw_Triggers!E6) -> 125.25 | D6: =AVERAGE(Raw_Triggers!D6,Raw_Triggers!F6) -> 76.35 | E6: =AVERAGE(Raw_Triggers!G6,Raw_Triggers!H6) -> 0.0515 | F6: =AVERAGE(Raw_Triggers!I6,Raw_Triggers!K6) -> 1.4448355 | G6: =AVERAGE(Raw_Triggers!J6,Raw_Triggers!L6) -> 3.5356733 | H6: =C6+0.5*D6 -> 163.425 | I6: =G6/F6 -> 2.4471113 | J6: =40*(H6-MIN($H$2:$H$21))/(MAX($H$2:$H$21)-MIN($H$2:$H$21))+30*(E6-MIN($E$2:$E$21))/(MAX($E$2:$E$21)-MIN($E$2:$E$21))+30*(I6-MIN($I$2:$I$21))/(MAX($I$2:$I$21)-MIN($I$2:$I$21)) -> 25.350622 | K6: =IF(J6<33,"Low",IF(J6<66,"Medium","High")) -> Low | L6: =Assumptions!$B$9 -> 70 | M6: =MAX(0,J6-L6) -> 0 | N6: =1120*M6 -> 0
A7: 2013 | B7: Palȍmϊnϊa | C7: =AVERAGE(Raw_Triggers!C7,Raw_Triggers!E7) -> 129.3 | D7: =AVERAGE(Raw_Triggers!D7,Raw_Triggers!F7) -> 80.3 | E7: =AVERAGE(Raw_Triggers!G7,Raw_Triggers!H7) -> 0.0732 | F7: =AVERAGE(Raw_Triggers!I7,Raw_Triggers!K7) -> 1.3725199 | G7: =AVERAGE(Raw_Triggers!J7,Raw_Triggers!L7) -> 3.7003537 | H7: =C7+0.5*D7 -> 169.45 | I7: =G7/F7 -> 2.6960293 | J7: =40*(H7-MIN($H$2:$H$21))/(MAX($H$2:$H$21)-MIN($H$2:$H$21))+30*(E7-MIN($E$2:$E$21))/(MAX($E$2:$E$21)-MIN($E$2:$E$21))+30*(I7-MIN($I$2:$I$21))/(MAX($I$2:$I$21)-MIN($I$2:$I$21)) -> 89.293537 | K7: =IF(J7<33,"Low",IF(J7<66,"Medium","High")) -> High | L7: =Assumptions!$B$9 -> 70 | M7: =MAX(0,J7-L7) -> 19.293537 | N7: =1120*M7 -> 21608.762
A8: 2014 | B8: Ambernϊa | C8: =AVERAGE(Raw_Triggers!C8,Raw_Triggers!E8) -> 124.95 | D8: =AVERAGE(Raw_Triggers!D8,Raw_Triggers!F8) -> 76.25 | E8: =AVERAGE(Raw_Triggers!G8,Raw_Triggers!H8) -> 0.05145 | F8: =AVERAGE(Raw_Triggers!I8,Raw_Triggers!K8) -> 1.448844 | G8: =AVERAGE(Raw_Triggers!J8,Raw_Triggers!L8) -> 3.5029372 | H8: =C8+0.5*D8 -> 163.075 | I8: =G8/F8 -> 2.4177463 | J8: =40*(H8-MIN($H$2:$H$21))/(MAX($H$2:$H$21)-MIN($H$2:$H$21))+30*(E8-MIN($E$2:$E$21))/(MAX($E$2:$E$21)-MIN($E$2:$E$21))+30*(I8-MIN($I$2:$I$21))/(MAX($I$2:$I$21)-MIN($I$2:$I$21)) -> 21.915931 | K8: =IF(J8<33,"Low",IF(J8<66,"Medium","High")) -> Low | L8: =Assumptions!$B$9 -> 70 | M8: =MAX(0,J8-L8) -> 0 | N8: =1120*M8 -> 0
A9: 2014 | B9: Palȍmϊnϊa | C9: =AVERAGE(Raw_Triggers!C9,Raw_Triggers!E9) -> 129.2 | D9: =AVERAGE(Raw_Triggers!D9,Raw_Triggers!F9) -> 80.3 | E9: =AVERAGE(Raw_Triggers!G9,Raw_Triggers!H9) -> 0.0744 | F9: =AVERAGE(Raw_Triggers!I9,Raw_Triggers!K9) -> 1.3737214 | G9: =AVERAGE(Raw_Triggers!J9,Raw_Triggers!L9) -> 3.6821127 | H9: =C9+0.5*D9 -> 169.35 | I9: =G9/F9 -> 2.6803926 | J9: =40*(H9-MIN($H$2:$H$21))/(MAX($H$2:$H$21)-MIN($H$2:$H$21))+30*(E9-MIN($E$2:$E$21))/(MAX($E$2:$E$21)-MIN($E$2:$E$21))+30*(I9-MIN($I$2:$I$21))/(MAX($I$2:$I$21)-MIN($I$2:$I$21)) -> 89.063703 | K9: =IF(J9<33,"Low",IF(J9<66,"Medium","High")) -> High | L9: =Assumptions!$B$9 -> 70 | M9: =MAX(0,J9-L9) -> 19.063703 | N9: =1120*M9 -> 21351.347
A10: 2015 | B10: Ambernϊa | C10: =AVERAGE(Raw_Triggers!C10,Raw_Triggers!E10) -> 124.65 | D10: =AVERAGE(Raw_Triggers!D10,Raw_Triggers!F10) -> 76.15 | E10: =AVERAGE(Raw_Triggers!G10,Raw_Triggers!H10) -> 0.0513 | F10: =AVERAGE(Raw_Triggers!I10,Raw_Triggers!K10) -> 1.4530408 | G10: =AVERAGE(Raw_Triggers!J10,Raw_Triggers!L10) -> 3.4696914 | H10: =C10+0.5*D10 -> 162.725 | I10: =G10/F10 -> 2.387883 | J10: =40*(H10-MIN($H$2:$H$21))/(MAX($H$2:$H$21)-MIN($H$2:$H$21))+30*(E10-MIN($E$2:$E$21))/(MAX($E$2:$E$21)-MIN($E$2:$E$21))+30*(I10-MIN($I$2:$I$21))/(MAX($I$2:$I$21)-MIN($I$2:$I$21)) -> 18.35243 | K10: =IF(J10<33,"Low",IF(J10<66,"Medium","High")) -> Low | L10: =Assumptions!$B$9 -> 70 | M10: =MAX(0,J10-L10) -> 0 | N10: =1120*M10 -> 0
A11: 2015 | B11: Palȍmϊnϊa | C11: =AVERAGE(Raw_Triggers!C11,Raw_Triggers!E11) -> 129.15 | D11: =AVERAGE(Raw_Triggers!D11,Raw_Triggers!F11) -> 80.25 | E11: =AVERAGE(Raw_Triggers!G11,Raw_Triggers!H11) -> 0.07555 | F11: =AVERAGE(Raw_Triggers!I11,Raw_Triggers!K11) -> 1.3748888 | G11: =AVERAGE(Raw_Triggers!J11,Raw_Triggers!L11) -> 3.6628747 | H11: =C11+0.5*D11 -> 169.275 | I11: =G11/F11 -> 2.6641244 | J11: =40*(H11-MIN($H$2:$H$21))/(MAX($H$2:$H$21)-MIN($H$2:$H$21))+30*(E11-MIN($E$2:$E$21))/(MAX($E$2:$E$21)-MIN($E$2:$E$21))+30*(I11-MIN($I$2:$I$21))/(MAX($I$2:$I$21)-MIN($I$2:$I$21)) -> 88.859736 | K11: =IF(J11<33,"Low",IF(J11<66,"Medium","High")) -> High | L11: =Assumptions!$B$9 -> 70 | M11: =MAX(0,J11-L11) -> 18.859736 | N11: =1120*M11 -> 21122.905
A12: 2016 | B12: Ambernϊa | C12: =AVERAGE(Raw_Triggers!C12,Raw_Triggers!E12) -> 124.3 | D12: =AVERAGE(Raw_Triggers!D12,Raw_Triggers!F12) -> 76 | E12: =AVERAGE(Raw_Triggers!G12,Raw_Triggers!H12) -> 0.05125 | F12: =AVERAGE(Raw_Triggers!I12,Raw_Triggers!K12) -> 1.45736 | G12: =AVERAGE(Raw_Triggers!J12,Raw_Triggers!L12) -> 3.4359879 | H12: =C12+0.5*D12 -> 162.3 | I12: =G12/F12 -> 2.3576796 | J12: =40*(H12-MIN($H$2:$H$21))/(MAX($H$2:$H$21)-MIN($H$2:$H$21))+30*(E12-MIN($E$2:$E$21))/(MAX($E$2:$E$21)-MIN($E$2:$E$21))+30*(I12-MIN($I$2:$I$21))/(MAX($I$2:$I$21)-MIN($I$2:$I$21)) -> 14.525589 | K12: =IF(J12<33,"Low",IF(J12<66,"Medium","High")) -> Low | L12: =Assumptions!$B$9 -> 70 | M12: =MAX(0,J12-L12) -> 0 | N12: =1120*M12 -> 0
A13: 2016 | B13: Palȍmϊnϊa | C13: =AVERAGE(Raw_Triggers!C13,Raw_Triggers!E13) -> 129.1 | D13: =AVERAGE(Raw_Triggers!D13,Raw_Triggers!F13) -> 80.15 | E13: =AVERAGE(Raw_Triggers!G13,Raw_Triggers!H13) -> 0.07675 | F13: =AVERAGE(Raw_Triggers!I13,Raw_Triggers!K13) -> 1.376018 | G13: =AVERAGE(Raw_Triggers!J13,Raw_Triggers!L13) -> 3.6426964 | H13: =C13+0.5*D13 -> 169.175 | I13: =G13/F13 -> 2.6472739 | J13: =40*(H13-MIN($H$2:$H$21))/(MAX($H$2:$H$21)-MIN($H$2:$H$21))+30*(E13-MIN($E$2:$E$21))/(MAX($E$2:$E$21)-MIN($E$2:$E$21))+30*(I13-MIN($I$2:$I$21))/(MAX($I$2:$I$21)-MIN($I$2:$I$21)) -> 88.555719 | K13: =IF(J13<33,"Low",IF(J13<66,"Medium","High")) -> High | L13: =Assumptions!$B$9 -> 70 | M13: =MAX(0,J13-L13) -> 18.555719 | N13: =1120*M13 -> 20782.406
... A21: 2020 | B21: Palȍmϊnϊa | C21: =AVERAGE(Raw_Triggers!C21,Raw_Triggers!E21) -> 128.8 | D21: =AVERAGE(Raw_Triggers!D21,Raw_Triggers!F21) -> 80 | E21: =AVERAGE(Raw_Triggers!G21,Raw_Triggers!H21) -> 0.08165 | F21: =AVERAGE(Raw_Triggers!I21,Raw_Triggers!K21) -> 1.3807646 | G21: =AVERAGE(Raw_Triggers!J21,Raw_Triggers!L21) -> 3.5550243 | H21: =C21+0.5*D21 -> 168.8 | I21: =G21/F21 -> 2.5746781 | J21: =40*(H21-MIN($H$2:$H$21))/(MAX($H$2:$H$21)-MIN($H$2:$H$21))+30*(E21-MIN($E$2:$E$21))/(MAX($E$2:$E$21)-MIN($E$2:$E$21))+30*(I21-MIN($I$2:$I$21))/(MAX($I$2:$I$21)-MIN($I$2:$I$21)) -> 87.23425 | K21: =IF(J21<33,"Low",IF(J21<66,"Medium","High")) -> High | L21: =Assumptions!$B$9 -> 70 | M21: =MAX(0,J21-L21) -> 17.23425 | N21: =1120*M21 -> 19302.36

Sheet Economic_Market_Data
A1: Year | B1: Country | C1: GDP per Person | D1: GNI per Person | E1: CPI (2016=100) | F1: Population | G1: Population Density | H1: Healthcare Spending per Person | I1: Household Savings Rate
A2: 2011 | B2: Palȍmϊnϊa | C2: 5872.57 | D2: 13044.98 | E2: 68.51 | F2: 21466283 | G2: 102.8 | H2: N/A | I2: 0.0496
A3: 2011 | B3: Ambernϊa | C3: 50944.4 | D3: 35364.09 | E3: 94.08 | F3: 4719607 | G3: 48.5 | H3: N/A | I3: 0.1037
A4: 2012 | B4: Palȍmϊnϊa | C4: 6830.67 | D4: 13836.06 | E4: 73.92 | F4: 21572541 | G4: 103.3 | H4: 354.33 | I4: 0.0153
A5: 2012 | B5: Ambernϊa | C5: 51687.99 | D5: 37486.51 | E5: 95.11 | F5: 4757367 | G5: 48.89 | H5: 4845.23 | I5: 0.0997
A6: 2013 | B6: Palȍmϊnϊa | C6: 7014.87 | D6: 14252.52 | E6: 78.84 | F6: 21685510 | G6: 103.85 | H6: 374.62 | I6: 0.015
A7: 2013 | B7: Ambernϊa | C7: 53451.96 | D7: 38473.99 | E7: 96.85 | F7: 4796557 | G7: 49.29 | H7: 4997.79 | I7: 0.1091
A8: 2014 | B8: Palȍmϊnϊa | C8: 7294.23 | D8: 14865.17 | E8: 85.63 | F8: 21798094 | G8: 104.39 | H8: 482.88 | I8: 0.0255
A9: 2014 | B9: Ambernϊa | C9: 53920.15 | D9: 38516.61 | E9: 98.39 | F9: 4838846 | G9: 49.73 | H9: 5051 | I9: 0.1105
A10: 2015 | B10: Palȍmϊnϊa | C10: 7429.09 | D10: 15185.9 | E10: 91.21 | F10: 21921299 | G10: 104.97 | H10: 504.45 | I10: 0.0227
A11: 2015 | B11: Ambernϊa | C11: 55000.5 | D11: 38988.05 | E11: 99.36 | F11: 4886134 | G11: 50.22 | H11: 5152.58 | I11: 0.1068
A12: 2016 | B12: Palȍmϊnϊa | C12: 7864.54 | D12: 16187.33 | E12: 100 | F12: 22038783 | G12: 105.54 | H12: 529.91 | I12: 0.0231
A13: 2016 | B13: Ambernϊa | C13: 58727.5 | D13: 41577.25 | E13: 100 | F13: 4935653 | G13: 50.72 | H13: 5414.8 | I13: 0.1392
A14: 2017 | B14: Palȍmϊnϊa | C14: 8135.29 | D14: 16697.33 | E14: 105.62 | F14: 22156566 | G14: 106.1 | H14: 557.7 | I14: 0.0416
A15: 2017 | B15: Ambernϊa | C15: 59948.83 | D15: 41720.75 | E15: 103.17 | F15: 4989994 | G15: 51.28 | H15: 5573.14 | I15: 0.1356
... A19: 2019 | B19: Ambernϊa | C19: 63593.9 | D19: 44143.25 | E19: 105.86 | F19: 5088243 | G19: 52.29 | H19: 5814.01 | I19: 0.147
A20: 2020 | B20: Palȍmϊnϊa | C20: 9705.48 | D20: 20138.9 | E20: 130.56 | F20: 22533810 | G20: 107.91 | H20: 706.55 | I20: N/A
A21: 2020 | B21: Ambernϊa | C21: 64865.73 | D21: 44210.48 | E21: 106.1 | F21: 5132634 | G21: 52.75 | H21: 5994.29 | I21: 0.1346

Sheet NEW_WORLD_Financials
A1: Income Statement | E1: Balance Sheet
A2: Income Statement | E2: Balance Sheet
A3: For the Year-Ended December 31, 2020 | E3: For the Year-Ended December 31, 2020
A4: (ψ in millions) | E4: (ψ in millions)
B5: 2020 | C5: 2019 | F5: 2020 | G5: 2019
A7: Revenue | E7: Assets
A8: Gross premiums written | B8: 14565 | C8: 14022 | E8: Cash | F8: 2891 | G8: 5351
A9: Less reinsurance ceded | B9: 1475 | C9: 1633 | E9: Investments | F9: 52264 | G9: 48089
E10: Accounts receivable | F10: 17 | G10: 333
A11: Net premiums written | B11: 13090 | C11: 12389 | E11: Deferred policy acquisition expenses | F11: 978 | G11: 939
A12: Increase in reserve for unearned premiums | B12: -448 | C12: -407 | E12: Property and equipment | F12: 7558 | G12: 7122
E13: Intangible assets | F13: 69 | G13: 85
A14: Net premiums earned | B14: 12642 | C14: 11982
F15: 63777 | G15: 61919
A16: Claims and Operating Expenses
A17: Net claims incurred | B17: 5227 | C17: 4564 | E17: Liabilities
A18: Net adjusting expense | B18: 1495 | C18: 956 | E18: Accounts payable | F18: 79 | G18: 717
A19: Commissions | B19: 1318 | C19: 1237 | E19: Unearned premium reserve | F19: 7454 | G19: 6996
A20: Salaries and fees | B20: 1511 | C20: 1076 | E20: Provision for unpaid claims | F20: 16651 | G20: 17839
A21: Amortization of property and equipment | B21: 145 | C21: 41
A22: Amortization of intangible assets | B22: 62 | C22: 83 | F22: 24184 | G22: 25552
A23: Other expenses | B23: 1183 | C23: 1000
E24: Shareholders' Equity | F24: 39593 | G24: 36367
B25: 10941 | C25: 8957
E26: Liabilities and Shareholders' Equity | F26: 63777 | G26: 61919
A27: Net Underwriting Income | B27: 1701 | C27: 3025
A29: Other Income
A30: Investment income | B30: 3272 | C30: 2778
A31: Miscellaneous | B31: 155 | C31: 7
B33: 3427 | C33: 2785
A35: Income Before Income Tax Expense | B35: 5128 | C35: 5810
A37: Income Tax Expense | B37: -1313 | C37: -1488
A39: Net Income for the Year | B39: 3815 | C39: 4322

Sheet Assumptions
A1: Parametric Health Insurance - Model Assumptions
A3: Assumption | B3: Value | C3: Purpose | D3: Comment
A4: Target buyer | B4: Government / healthcare organization | C4: Product design | D4: Institutional product, not individual retail insurance
A5: Country focus | B5: Palȍmϊnϊa or Ambernϊa | C5: Market selection | D5: Both countries are kept in the cleaned data so the final choice can be justified.
A6: Trigger variables | B6: Blood Pressure, Diabetes, Cholesterol | C6: Trigger design | D6: Variables are measurable, health-related, and available in the SOA case workbook.
A7: Health index weights | B7: 40% BP, 30% Diabetes, 30% Cholesterol | C7: Index construction | D7: Initial judgmental weights; PCA can be used as an alternative data-driven weighting method.
A8: Payout factor | B8: 1120 | C8: Payout structure | D8: Payout = 1120 × excess over estimated health index threshold.
A9: Trigger threshold | B9: 70 | C9: Trigger event | D9: Threshold can be set by historical percentile, risk appetite, or affordability analysis. Current value is illustrative.
A10: Premium principle | B10: Equivalence principle | C10: Pricing | D10: Basic premium = expected payout plus loading.
A11: Monte Carlo use | B11: Simulate health index / payout distribution | C11: Risk assessment | D11: Use fitted/assumed distributions for trigger variables to estimate expected payout and tail risk.
A12: Main limitation | B12: Basis risk | C12: Risk discussion | D12: Payout may not perfectly match actual healthcare losses.

Sheet Correlation_PCA_Input
A1: Correlation and PCA Input
A3: Year | B3: Country | C3: BP Component | D3: Avg Diabetes | E3: Cholesterol Ratio | G3: Correlation Matrix | H3: BP Component | I3: Avg Diabetes | J3: Cholesterol Ratio
A4: =Model_Input!A2 -> 2011 | B4: =Model_Input!B2 -> Ambernϊa | C4: =Model_Input!H2 -> 164.175 | D4: =Model_Input!E2 -> 0.05165 | E4: =Model_Input!I2 -> 2.5043422 | G4: BP Component | H4: =CORREL($C$4:$C$23,$C$4:$C$23) -> 1 | I4: =CORREL($C$4:$C$23,$D$4:$D$23) -> 0.94787609 | J4: =CORREL($C$4:$C$23,$E$4:$E$23) -> 0.96904459
A5: =Model_Input!A3 -> 2011 | B5: =Model_Input!B3 -> Palȍmϊnϊa | C5: =Model_Input!H3 -> 169.575 | D5: =Model_Input!E3 -> 0.07075 | E5: =Model_Input!I3 -> 2.7259212 | G5: Avg Diabetes | H5: =CORREL($D$4:$D$23,$C$4:$C$23) -> 0.94787609 | I5: =CORREL($D$4:$D$23,$D$4:$D$23) -> 1 | J5: =CORREL($D$4:$D$23,$E$4:$E$23) -> 0.84029005
A6: =Model_Input!A4 -> 2012 | B6: =Model_Input!B4 -> Ambernϊa | C6: =Model_Input!H4 -> 163.85 | D6: =Model_Input!E4 -> 0.0516 | E6: =Model_Input!I4 -> 2.4758708 | G6: Cholesterol Ratio | H6: =CORREL($E$4:$E$23,$C$4:$C$23) -> 0.96904459 | I6: =CORREL($E$4:$E$23,$D$4:$D$23) -> 0.84029005 | J6: =CORREL($E$4:$E$23,$E$4:$E$23) -> 1
A7: =Model_Input!A5 -> 2012 | B7: =Model_Input!B5 -> Palȍmϊnϊa | C7: =Model_Input!H5 -> 169.5 | D7: =Model_Input!E5 -> 0.07195 | E7: =Model_Input!I5 -> 2.7111297
A8: =Model_Input!A6 -> 2013 | B8: =Model_Input!B6 -> Ambernϊa | C8: =Model_Input!H6 -> 163.425 | D8: =Model_Input!E6 -> 0.0515 | E8: =Model_Input!I6 -> 2.4471113
A9: =Model_Input!A7 -> 2013 | B9: =Model_Input!B7 -> Palȍmϊnϊa | C9: =Model_Input!H7 -> 169.45 | D9: =Model_Input!E7 -> 0.0732 | E9: =Model_Input!I7 -> 2.6960293 | G9: PCA workflow | H9: 1. Standardize BP, Diabetes, and Cholesterol variables.
A10: =Model_Input!A8 -> 2014 | B10: =Model_Input!B8 -> Ambernϊa | C10: =Model_Input!H8 -> 163.075 | D10: =Model_Input!E8 -> 0.05145 | E10: =Model_Input!I8 -> 2.4177463 | H10: 2. Compute covariance/correlation matrix.
A11: =Model_Input!A9 -> 2014 | B11: =Model_Input!B9 -> Palȍmϊnϊa | C11: =Model_Input!H9 -> 169.35 | D11: =Model_Input!E9 -> 0.0744 | E11: =Model_Input!I9 -> 2.6803926 | H11: 3. Extract first principal component as data-driven health index.
A12: =Model_Input!A10 -> 2015 | B12: =Model_Input!B10 -> Ambernϊa | C12: =Model_Input!H10 -> 162.725 | D12: =Model_Input!E10 -> 0.0513 | E12: =Model_Input!I10 -> 2.387883 | H12: 4. Compare PCA-based index with judgmental weighted index.
A13: =Model_Input!A11 -> 2015 | B13: =Model_Input!B11 -> Palȍmϊnϊa | C13: =Model_Input!H11 -> 169.275 | D13: =Model_Input!E11 -> 0.07555 | E13: =Model_Input!I11 -> 2.6641244 | H13: 5. Select trigger threshold based on percentile/risk appetite.
A14: =Model_Input!A12 -> 2016 | B14: =Model_Input!B12 -> Ambernϊa | C14: =Model_Input!H12 -> 162.3 | D14: =Model_Input!E12 -> 0.05125 | E14: =Model_Input!I12 -> 2.3576796
A15: =Model_Input!A13 -> 2016 | B15: =Model_Input!B13 -> Palȍmϊnϊa | C15: =Model_Input!H13 -> 169.175 | D15: =Model_Input!E13 -> 0.07675 | E15: =Model_Input!I13 -> 2.6472739
A16: =Model_Input!A14 -> 2017 | B16: =Model_Input!B14 -> Ambernϊa | C16: =Model_Input!H14 -> 161.95 | D16: =Model_Input!E14 -> 0.0512 | E16: =Model_Input!I14 -> 2.3271627
A17: =Model_Input!A15 -> 2017 | B17: =Model_Input!B15 -> Palȍmϊnϊa | C17: =Model_Input!H15 -> 169.125 | D17: =Model_Input!E15 -> 0.07795 | E17: =Model_Input!I15 -> 2.6299375
A18: =Model_Input!A16 -> 2018 | B18: =Model_Input!B16 -> Ambernϊa | C18: =Model_Input!H16 -> 161.6 | D18: =Model_Input!E16 -> 0.05115 | E18: =Model_Input!I16 -> 2.2965472
A19: =Model_Input!A17 -> 2018 | B19: =Model_Input!B17 -> Palȍmϊnϊa | C19: =Model_Input!H17 -> 169.05 | D19: =Model_Input!E17 -> 0.07915 | E19: =Model_Input!I17 -> 2.6120072
A20: =Model_Input!A18 -> 2019 | B20: =Model_Input!B18 -> Ambernϊa | C20: =Model_Input!H18 -> 161.2 | D20: =Model_Input!E18 -> 0.0512 | E20: =Model_Input!I18 -> 2.2658079
A21: =Model_Input!A19 -> 2019 | B21: =Model_Input!B19 -> Palȍmϊnϊa | C21: =Model_Input!H19 -> 168.95 | D21: =Model_Input!E19 -> 0.0804 | E21: =Model_Input!I19 -> 2.5935328
A22: =Model_Input!A20 -> 2020 | B22: =Model_Input!B20 -> Ambernϊa | C22: =Model_Input!H20 -> 160.775 | D22: =Model_Input!E20 -> 0.0513 | E22: =Model_Input!I20 -> 2.2350325
A23: =Model_Input!A21 -> 2020 | B23: =Model_Input!B21 -> Palȍmϊnϊa | C23: =Model_Input!H21 -> 168.8 | D23: =Model_Input!E21 -> 0.08165 | E23: =Model_Input!I21 -> 2.5746781
